MANIFEST.in
README.md
requirements.txt
setup.py
deployment/__init__.py
deployment/admin.py
deployment/bb.py
deployment/fabfile.py
deployment/models.py
deployment/tests.py
deployment/utils.py
deployment/views.py
deployment/cookbooks/deployment/README.md
deployment/cookbooks/deployment/chefignore
deployment/cookbooks/deployment/metadata.rb
deployment/cookbooks/deployment/recipes/default.rb
deployment/cookbooks/deployment/recipes/setup_postgres.rb
deployment/cookbooks/deployment/spec/spec_helper.rb
deployment/cookbooks/deployment/spec/unit/recipes/default_spec.rb
deployment/cookbooks/deployment/templates/default/placeholder
deployment/management/__init__.py
deployment/management/commands/__init__.py
deployment/management/commands/create_rackspace_server.py
deployment/management/commands/deploy.py
deployment/templates/deployment/local_settings.py.erb
deployment/templates/deployment/logrotate.erb
deployment/templates/deployment/nginx.conf.erb
deployment/templates/deployment/run_celery.sh.erb
deployment/templates/deployment/run_gunicorn.sh.erb
deployment/templates/deployment/upstart_celery.conf.erb
deployment/templates/deployment/upstart_gunicorn.conf.erb
django_deployment.egg-info/PKG-INFO
django_deployment.egg-info/SOURCES.txt
django_deployment.egg-info/dependency_links.txt
django_deployment.egg-info/pbr.json
django_deployment.egg-info/requires.txt
django_deployment.egg-info/top_level.txt