Metadata-Version: 1.1
Name: django-deployment
Version: 0.1.4.5
Summary: A simple deployment Django library using Fabric and Chef
Home-page: http://www.example.com/
Author: Jean-Mark Wright
Author-email: jeanmark.wright@gmail.com
License: GPL v3 License
Platform: UNKNOWN
Classifier: Environment :: Web Environment
Classifier: Framework :: Django
Classifier: Intended Audience :: Developers
Classifier: License :: OSI Approved :: BSD License
Classifier: Operating System :: OS Independent
Classifier: Programming Language :: Python
Classifier: Programming Language :: Python :: 3
Classifier: Programming Language :: Python :: 3.2
Classifier: Programming Language :: Python :: 3.3
Classifier: Topic :: Internet :: WWW/HTTP
Classifier: Topic :: Internet :: WWW/HTTP :: Dynamic Content
